nort/__init__.py
nort/config.py
nort/nort.py
nort/note.py
nort/template.py
nort/util.py
nort-0.2.0.data/data/share/nort/nort.yaml
nort-0.2.0.data/scripts/nort
nort-0.2.0.dist-info/LICENSE
nort-0.2.0.dist-info/METADATA
nort-0.2.0.dist-info/WHEEL
nort-0.2.0.dist-info/top_level.txt
nort-0.2.0.dist-info/RECORD
