Metadata-Version: 2.1
Name: nort
Version: 0.2.0
Summary: A tool for creating and managing notes
Home-page: https://github.com/taDachs/nort
Author: Max Schik
Author-email: max.schik@googlemail.com
License: MIT
Platform: UNKNOWN
Classifier: Programming Language :: Python :: 3
Classifier: License :: OSI Approved :: MIT License
Classifier: Operating System :: OS Independent
Requires-Python: >=3.6
Requires-Dist: ruamel.yaml
